emoji.py
main.py
astrbot_plugin_create_meme-0.0.3.dist-info/licenses/LICENSE
astrbot_plugin_create_meme-0.0.3.dist-info/METADATA
astrbot_plugin_create_meme-0.0.3.dist-info/WHEEL
astrbot_plugin_create_meme-0.0.3.dist-info/top_level.txt
astrbot_plugin_create_meme-0.0.3.dist-info/RECORD
