Metadata-Version: 2.4
Name: astrbot_plugin_create_meme
Version: 0.0.3
Summary: 一个用于 astrbot 的宝藏袋插件
Home-page: https://github.com/xiaomizhoubaobei/astrbot_plugin_create_meme
Author: 祁筱欣
Author-email: mzapi@x.mizhoubaobei.top
Project-URL: Homepage, https://github.com/xiaomizhoubaobei/astrbot_plugin_create_meme
Project-URL: Download, https://github.com/xiaomizhoubaobei/astrbot_plugin_create_meme/releases
Project-URL: Issues, https://github.com/xiaomizhoubaobei/astrbot_plugin_create_meme/issues
Project-URL: Bug, https://github.com/xiaomizhoubaobei/astrbot_plugin_create_meme/issues
Project-URL: GitHub, https://github.com/xiaomizhoubaobei/astrbot_plugin_create_meme
Project-URL: Twitter, https://x.com/XinXiao12088
Project-URL: Pypi, https://pypi.org/project/astrbot_plugin_treasure_create_meme/
Classifier: Development Status :: 3 - Alpha
Classifier: Intended Audience :: Developers
Classifier: License :: OSI Approved :: MIT License
Classifier: Programming Language :: Python :: 3.10
Classifier: Programming Language :: Python :: 3.11
Classifier: Programming Language :: Python :: 3.12
Classifier: Programming Language :: Python :: 3.13
Requires-Python: >=3.10
License-File: LICENSE
Dynamic: author
Dynamic: author-email
Dynamic: classifier
Dynamic: description
Dynamic: description-content-type
Dynamic: home-page
Dynamic: license-file
Dynamic: project-url
Dynamic: requires-python
Dynamic: summary
